{
  "hash": "5e361093",
  "configHash": "f51d1720",
  "lockfileHash": "41014dad",
  "browserHash": "67e3d2c9",
  "optimized": {
    "react/jsx-dev-runtime": {
      "src": "../../node_modules/react/jsx-dev-runtime.js",
      "file": "react_jsx-dev-runtime.js",
      "fileHash": "93a3e92c",
      "needsInterop": true
    },
    "react-dom/client": {
      "src": "../../node_modules/react-dom/client.js",
      "file": "react-dom_client.js",
      "fileHash": "0158c402",
      "needsInterop": true
    },
    "react-router-dom": {
      "src": "../../node_modules/react-router-dom/dist/index.mjs",
      "file": "react-router-dom.js",
      "fileHash": "5e501b9c",
      "needsInterop": false
    },
    "react": {
      "src": "../../node_modules/react/index.js",
      "file": "react.js",
      "fileHash": "c03311e6",
      "needsInterop": true
    },
    "react-icons/fa": {
      "src": "../../node_modules/react-icons/fa/index.mjs",
      "file": "react-icons_fa.js",
      "fileHash": "78a59f10",
      "needsInterop": false
    },
    "antd": {
      "src": "../../node_modules/antd/es/index.js",
      "file": "antd.js",
      "fileHash": "8ffd8f24",
      "needsInterop": false
    },
    "@ant-design/icons": {
      "src": "../../node_modules/@ant-design/icons/es/index.js",
      "file": "@ant-design_icons.js",
      "fileHash": "f2c79063",
      "needsInterop": false
    },
    "axios": {
      "src": "../../node_modules/axios/index.js",
      "file": "axios.js",
      "fileHash": "7a870c2a",
      "needsInterop": false
    },
    "framer-motion": {
      "src": "../../node_modules/framer-motion/dist/es/index.mjs",
      "file": "framer-motion.js",
      "fileHash": "be6ddcfc",
      "needsInterop": false
    }
  },
  "chunks": {
    "chunk-TOMGHUTE": {
      "file": "chunk-TOMGHUTE.js"
    },
    "chunk-XE2STDAP": {
      "file": "chunk-XE2STDAP.js"
    },
    "chunk-D2KY6O3O": {
      "file": "chunk-D2KY6O3O.js"
    },
    "chunk-V4OQ3NZ2": {
      "file": "chunk-V4OQ3NZ2.js"
    }
  }
}